setup.py
django_parallelized_querysets.egg-info/PKG-INFO
django_parallelized_querysets.egg-info/SOURCES.txt
django_parallelized_querysets.egg-info/dependency_links.txt
django_parallelized_querysets.egg-info/not-zip-safe
django_parallelized_querysets.egg-info/requires.txt
django_parallelized_querysets.egg-info/top_level.txt
parallelized_querysets/__init__.py
parallelized_querysets/core.py