Metadata-Version: 1.1
Name: django-parallelized-querysets
Version: 0.0.4
Summary: Spread Django QuerySets on multiple cores with low memory usage.
Home-page: https://github.com/pelletier/django-parallelized_querysets
Author: Thomas Pelletier
Author-email: thomas@pelletier.im
License: MIT
Platform: UNKNOWN
Classifier: Development Status :: 2 - Pre-Alpha
Classifier: Framework :: Django
Classifier: Environment :: Web Environment
Classifier: Intended Audience :: Developers
Classifier: License :: OSI Approved :: MIT License
Classifier: Operating System :: OS Independent
Classifier: Programming Language :: Python :: 2.7
Classifier: Topic :: Software Development :: Libraries :: Python Modules
Classifier: Topic :: Utilities
